fastapi_overrider/__init__.py
fastapi_overrider-0.7.2.dist-info/LICENSE
fastapi_overrider-0.7.2.dist-info/METADATA
fastapi_overrider-0.7.2.dist-info/WHEEL
fastapi_overrider-0.7.2.dist-info/RECORD
