Metadata-Version: 2.1
Name: fastapi-overrider
Version: 0.7.2
Summary: FastAPI Dependency overrides made easy.
Home-page: https://github.com/phha/fastapi-overrider
License: MIT
Keywords: fastapi,pytest
Author: Philipp Hack
Author-email: philipp.hack@gmail.com
Requires-Python: >=3.10,<4.0
Classifier: Framework :: FastAPI
Classifier: Framework :: Pytest
Classifier: License :: OSI Approved :: MIT License
Classifier: Programming Language :: Python :: 3
Classifier: Programming Language :: Python :: 3.10
Classifier: Programming Language :: Python :: 3.11
Classifier: Programming Language :: Python :: 3.12
Provides-Extra: unifactory
Requires-Dist: fastapi (>=0.95.2)
Requires-Dist: pytest (>=7.3.1,<8.0.0)
Requires-Dist: unifactory (>=0.1.0,<0.2.0) ; extra == "unifactory"
Project-URL: Repository, https://github.com/phha/fastapi-overrider
